{
  "updated": "2026-05-05T10:15:31Z",
  "data": {
    "sp": {
      "price": 7200.75,
      "chgPct": -0.41,
      "src": "GHA"
    },
    "ndq": {
      "price": 25067.8,
      "chgPct": -0.19,
      "src": "GHA"
    },
    "dji": {
      "price": 48941.9,
      "chgPct": -1.13,
      "src": "GHA"
    },
    "inr": {
      "price": 95.26,
      "chgPct": 0.2,
      "src": "GHA"
    },
    "crude": {
      "price": 104.22,
      "chgPct": -0.16,
      "src": "GHA"
    },
    "gold": {
      "price": 4565.5,
      "chgPct": 0.46,
      "src": "GHA"
    },
    "silver": {
      "price": 74.11,
      "chgPct": 1.35,
      "src": "GHA"
    },
    "n50": {
      "price": 24032.8,
      "chgPct": -0.38,
      "src": "GHA"
    },
    "bn": {
      "price": 54547.05,
      "chgPct": -0.64,
      "src": "GHA"
    },
    "sx": {
      "price": 77017.79,
      "chgPct": -0.33,
      "src": "GHA"
    },
    "fn": {
      "price": 25716.9,
      "chgPct": -0.41,
      "src": "GHA"
    },
    "vix": {
      "price": 17.91,
      "chgPct": -2.0,
      "src": "GHA"
    },
    "t_RELIANCE": {
      "price": 1463.6,
      "chgPct": -0.23,
      "src": "GHA"
    },
    "t_HDFCBANK": {
      "price": 772.3,
      "chgPct": -0.92,
      "src": "GHA"
    },
    "t_ICICIBANK": {
      "price": 1251.3,
      "chgPct": -1.43,
      "src": "GHA"
    },
    "t_INFY": {
      "price": 1178.1,
      "chgPct": 0.87,
      "src": "GHA"
    },
    "t_TCS": {
      "price": 2427.3,
      "chgPct": -0.15,
      "src": "GHA"
    },
    "t_AIRTEL": {
      "price": 1806.1,
      "chgPct": -1.2,
      "src": "GHA"
    },
    "t_ITC": {
      "price": 311.45,
      "chgPct": 0.11,
      "src": "GHA"
    },
    "t_SBI": {
      "price": 1059.9,
      "chgPct": -0.8,
      "src": "GHA"
    },
    "t_KOTAK": {
      "price": 371.35,
      "chgPct": 0.07,
      "src": "GHA"
    },
    "t_LT": {
      "price": 4054.5,
      "chgPct": -1.1,
      "src": "GHA"
    },
    "u_AAPL": {
      "price": 276.83,
      "chgPct": 0.12,
      "src": "GHA"
    },
    "u_MSFT": {
      "price": 413.62,
      "chgPct": 0.2,
      "src": "GHA"
    },
    "u_NVDA": {
      "price": 198.48,
      "chgPct": 0.41,
      "src": "GHA"
    },
    "u_AMZN": {
      "price": 272.05,
      "chgPct": -0.03,
      "src": "GHA"
    },
    "u_GOOGL": {
      "price": 383.25,
      "chgPct": 0.09,
      "src": "GHA"
    },
    "u_META": {
      "price": 610.41,
      "chgPct": 0.12,
      "src": "GHA"
    },
    "u_TSLA": {
      "price": 392.51,
      "chgPct": 0.16,
      "src": "GHA"
    },
    "u_BRK": {
      "price": 468.52,
      "chgPct": -0.15,
      "src": "GHA"
    },
    "u_JPM": {
      "price": 307.65,
      "chgPct": -0.09,
      "src": "GHA"
    },
    "u_UNH": {
      "price": 370.75,
      "chgPct": 0.15,
      "src": "GHA"
    }
  },
  "errors": []
}